setup.py
bobsleigh/__init__.py
bobsleigh.egg-info/PKG-INFO
bobsleigh.egg-info/SOURCES.txt
bobsleigh.egg-info/dependency_links.txt
bobsleigh.egg-info/top_level.txt
bobsleigh/conf/__init__.py
bobsleigh/conf/handlers.py
bobsleigh/runner/__init__.py
bobsleigh/runner/monitor.py