Metadata-Version: 1.0
Name: bobsleigh
Version: 1.0.3
Summary: Helps write less code when configuring Django installations.
Home-page: http://github.com/seddonym/bobsleigh/
Author: David Seddon
Author-email: david@seddonym.me
License: UNKNOWN
Platform: UNKNOWN
